LICENSE
README.md
setup.py
bibtex2word/__init__.py
bibtex2word/__main__.py
bibtex2word.egg-info/PKG-INFO
bibtex2word.egg-info/SOURCES.txt
bibtex2word.egg-info/dependency_links.txt
bibtex2word.egg-info/entry_points.txt
bibtex2word.egg-info/requires.txt
bibtex2word.egg-info/top_level.txt