Metadata-Version: 2.1
Name: bibtex2word
Version: 0.0.3
Summary: My short description for my project.
Home-page: https://github.com/franceme/bibtex2word
Author: Myles Frantz
Author-email: frantzme@vt.edu
License: UNKNOWN
Platform: UNKNOWN
Classifier: Programming Language :: Python
Classifier: Programming Language :: Python :: 3
License-File: LICENSE
